betterqa/__init__.py
betterqa/__main__.py
betterqa/cli.py
betterqa-0.1.4.dist-info/LICENSE
betterqa-0.1.4.dist-info/METADATA
betterqa-0.1.4.dist-info/WHEEL
betterqa-0.1.4.dist-info/entry_points.txt
betterqa-0.1.4.dist-info/RECORD
