Metadata-Version: 2.1
Name: betterqa
Version: 0.1.4
Summary: An Utility for QA Testers
License: MIT
Author: Govardhan Ummadisetty
Author-email: vardhank9@gmail.com
Requires-Python: >=3.12,<4.0
Classifier: License :: OSI Approved :: MIT License
Classifier: Programming Language :: Python :: 3
Classifier: Programming Language :: Python :: 3.12
Requires-Dist: rich (>=13.8.1,<14.0.0)
Requires-Dist: typer (>=0.12.5,<0.13.0)
